newsarchives/__init__.py
newsarchives-0.1.1.dist-info/METADATA
newsarchives-0.1.1.dist-info/WHEEL
newsarchives-0.1.1.dist-info/top_level.txt
newsarchives-0.1.1.dist-info/RECORD
