Metadata-Version: 2.1
Name: newsarchives
Version: 0.1.1
Summary: The official python wrapper for the News Archives API
Home-page: https://github.com/gadhagod/News-Archives
Author: Aarav Borthakur
Author-email: gadhaguy13@gmail.com
License: UNKNOWN
Platform: UNKNOWN
Classifier: Programming Language :: Python :: 3
Classifier: License :: OSI Approved :: MIT License
Classifier: Operating System :: OS Independent
Requires-Python: >=3.6
Requires-Dist: requests
